aionui/__init__.py
aionui/aionui.py
aionui/config/__init__.py
aionui/config/config.py
aionui/enums/__init__.py
aionui/enums/keyboard_command.py
aionui/enums/platform.py
aionui/exceptions/__init__.py
aionui/exceptions/bot_detected_exception.py
aionui/models/__init__.py
aionui/models/base.py
aionui/models/claude.py
aionui/models/deep_seek.py
aionui/models/gemini.py
aionui/models/gpt.py
aionui/models_async/__init__.py
aionui/models_async/base_async.py
aionui/models_async/claude_async.py
aionui/models_async/deep_seek_async.py
aionui/models_async/gemini_async.py
aionui/models_async/gpt_async.py
aionui/utils/common.py
aionui/utils/logger.py
aionui/utils/singleton.py
aionui-1.4.2.dist-info/LICENSE
aionui-1.4.2.dist-info/METADATA
aionui-1.4.2.dist-info/WHEEL
aionui-1.4.2.dist-info/RECORD
