Metadata-Version: 2.3
Name: aionui
Version: 1.4.2
Summary: A powerful Python library for automating interactions with AI models (ChatGPT, Claude, Gemini) through their web interfaces using Playwright. Supports both synchronous and asynchronous operations, file handling, and multi-platform compatibility.
License: MIT
Author: AnhHoang
Author-email: vutrianhhoang@gmail.com
Requires-Python: >=3.10,<4.0
Classifier: Development Status :: 4 - Beta
Classifier: Framework :: AsyncIO
Classifier: Framework :: Pytest
Classifier: Intended Audience :: Developers
Classifier: License :: OSI Approved :: MIT License
Classifier: Operating System :: OS Independent
Classifier: Programming Language :: Python :: 3
Classifier: Programming Language :: Python :: 3.10
Classifier: Programming Language :: Python :: 3.11
Classifier: Programming Language :: Python :: 3.12
Classifier: Programming Language :: Python :: 3.13
Classifier: Topic :: Internet :: WWW/HTTP :: Browsers
Classifier: Topic :: Scientific/Engineering :: Artificial Intelligence
Classifier: Topic :: Software Development :: Libraries :: Python Modules
Classifier: Topic :: Software Development :: Testing
Classifier: Typing :: Typed
Requires-Dist: aiohttp (>=3.11.11,<4.0.0)
Requires-Dist: black (>=24.10.0,<25.0.0)
Requires-Dist: nest-asyncio (>=1.6.0,<2.0.0)
Requires-Dist: playwright (>=1.49.1,<2.0.0)
Requires-Dist: pydantic (>=2.10.4,<3.0.0)
Requires-Dist: pyperclip (>=1.9.0,<2.0.0)
Requires-Dist: pyyaml (>=6.0.2,<7.0.0)
Requires-Dist: requests (>=2.32.3,<3.0.0)
Requires-Dist: tenacity (>=9.0.0,<10.0.0)
